darfix/__init__.py
darfix/_config.py
darfix/_version.py
darfix/dtypes.py
darfix/main.py
darfix/math.py
darfix/pixel_sizes.py
darfix/core/__init__.py
darfix/core/array_utils.py
darfix/core/autofocus.py
darfix/core/components_matching.py
darfix/core/data_path_finder.py
darfix/core/data_selection.py
darfix/core/dataset.py
darfix/core/dimension.py
darfix/core/fscan_parser.py
darfix/core/grainplot.py
darfix/core/image_registration.py
darfix/core/image_stack.py
darfix/core/mapping.py
darfix/core/moment_types.py
darfix/core/noise_removal.py
darfix/core/noise_removal_type.py
darfix/core/positioners.py
darfix/core/rocking_curves.py
darfix/core/rocking_curves_map.py
darfix/core/roi.py
darfix/core/settings.py
darfix/core/shift_correction.py
darfix/core/state_of_operation.py
darfix/core/transformation.py
darfix/core/utils.py
darfix/core/zigzag_mode.py
darfix/decomposition/__init__.py
darfix/decomposition/base.py
darfix/decomposition/ipca.py
darfix/decomposition/nica.py
darfix/decomposition/nmf.py
darfix/decomposition/pca.py
darfix/gui/__init__.py
darfix/gui/binning_widget.py
darfix/gui/blind_source_separation_widget.py
darfix/gui/choose_dimensions.py
darfix/gui/concatenate_scans.py
darfix/gui/dimensions_widget.py
darfix/gui/display_components_widget.py
darfix/gui/filter_by_dimension.py
darfix/gui/magnification_widget.py
darfix/gui/metadata_widget.py
darfix/gui/pca_widget.py
darfix/gui/projection_widget.py
darfix/gui/roi_limits_toolbar.py
darfix/gui/roi_selection_widget.py
darfix/gui/rsm_histogram_widget.py
darfix/gui/rsm_widget.py
darfix/gui/weak_beam_widget.py
darfix/gui/zsum_widget.py
darfix/gui/configuration/__init__.py
darfix/gui/configuration/action.py
darfix/gui/configuration/level.py
darfix/gui/data_selection/__init__.py
darfix/gui/data_selection/hdf5_dataset_selection_widget.py
darfix/gui/data_selection/line_edits.py
darfix/gui/data_selection/scan_selection_widgets.py
darfix/gui/data_selection/utils.py
darfix/gui/data_selection/working_dir_selection_widget.py
darfix-4.3.1.dist-info/licenses/LICENSE
darfix-4.3.1.dist-info/METADATA
darfix-4.3.1.dist-info/WHEEL
darfix-4.3.1.dist-info/entry_points.txt
darfix-4.3.1.dist-info/top_level.txt
darfix-4.3.1.dist-info/RECORD
