Metadata-Version: 2.4
Name: darfix
Version: 4.3.1
Summary: Computer vision software for the interpretation of diffraction images
Author-email: ESRF <dau-pydev@esrf.fr>
License: The MIT license follows:
Project-URL: Homepage, https://gitlab.esrf.fr/XRD/darfix/
Project-URL: Documentation, http://www.edna-site.org/pub/doc/darfix/latest
Project-URL: Repository, https://gitlab.esrf.fr/XRD/darfix/
Project-URL: Issues, https://gitlab.esrf.fr/XRD/darfix/issues
Project-URL: Changelog, https://gitlab.esrf.fr/XRD/darfix/-/blob/main/CHANGELOG.md
Keywords: orange3 add-on,ewoks
Classifier: Intended Audience :: Science/Research
Classifier: License :: OSI Approved :: MIT License
Classifier: Programming Language :: Python :: 3
Requires-Python: >=3.8
License-File: LICENSE
Requires-Dist: numpy<3
Requires-Dist: numba
Requires-Dist: silx<3,>=2.2.0
Requires-Dist: matplotlib
Requires-Dist: PyOpenGL
Requires-Dist: ewoks>=1.0.0
Requires-Dist: packaging
Requires-Dist: scikit-learn
Requires-Dist: scipy
Requires-Dist: tqdm
Requires-Dist: joblib
Requires-Dist: esrf-pathlib
Requires-Dist: colorstamps
Requires-Dist: eval_type_backport
Provides-Extra: full-noqt
Requires-Dist: opencv-python-headless>=4.3.0.36; extra == "full-noqt"
Requires-Dist: scikit-image>=0.17.1; extra == "full-noqt"
Requires-Dist: ewoksorange>=3.0.0; extra == "full-noqt"
Requires-Dist: hdf5plugin; extra == "full-noqt"
Provides-Extra: full
Requires-Dist: darfix[full_noqt]; extra == "full"
Requires-Dist: PyQt6; extra == "full"
Provides-Extra: test
Requires-Dist: darfix[full]; extra == "test"
Requires-Dist: pytest; extra == "test"
Provides-Extra: dev
Requires-Dist: darfix[test]; extra == "dev"
Requires-Dist: black; extra == "dev"
Requires-Dist: flake8>=4; extra == "dev"
Requires-Dist: flake8_nb>=0.3.1; extra == "dev"
Requires-Dist: isort; extra == "dev"
Provides-Extra: doc
Requires-Dist: darfix[test]; extra == "doc"
Requires-Dist: sphinx<9,>=7.2; extra == "doc"
Requires-Dist: sphinx-autodoc-typehints>=1.16; extra == "doc"
Requires-Dist: sphinxcontrib-video; extra == "doc"
Requires-Dist: sphinx-copybutton; extra == "doc"
Requires-Dist: nbsphinx; extra == "doc"
Requires-Dist: ipykernel; extra == "doc"
Requires-Dist: recommonmark; extra == "doc"
Requires-Dist: pydata_sphinx_theme; extra == "doc"
Requires-Dist: ewokssphinx>=1.0.0; extra == "doc"
Requires-Dist: sphinx_design; extra == "doc"
Dynamic: license-file
